spark_plotting_tools/__init__.py
spark_plotting_tools/functions/__init__.py
spark_plotting_tools/functions/generator.py
spark_plotting_tools/utils/__init__.py
spark_plotting_tools/utils/color.py
spark_plotting_tools-0.3.0.dist-info/LICENSE
spark_plotting_tools-0.3.0.dist-info/METADATA
spark_plotting_tools-0.3.0.dist-info/WHEEL
spark_plotting_tools-0.3.0.dist-info/top_level.txt
spark_plotting_tools-0.3.0.dist-info/RECORD
